ultralytics/__init__.py
ultralytics/assets/bus.jpg
ultralytics/assets/zidane.jpg
ultralytics/datasets/Argoverse.yaml
ultralytics/datasets/GlobalWheat2020.yaml
ultralytics/datasets/ImageNet.yaml
ultralytics/datasets/Objects365.yaml
ultralytics/datasets/SKU-110K.yaml
ultralytics/datasets/VOC.yaml
ultralytics/datasets/VisDrone.yaml
ultralytics/datasets/coco.yaml
ultralytics/datasets/coco128-seg.yaml
ultralytics/datasets/coco128.yaml
ultralytics/datasets/coco8-seg.yaml
ultralytics/datasets/coco8.yaml
ultralytics/datasets/face.yaml
ultralytics/datasets/xView.yaml
ultralytics/detect/__init__.py
ultralytics/detect/predict_face.py
ultralytics/hub/__init__.py
ultralytics/hub/auth.py
ultralytics/hub/session.py
ultralytics/hub/utils.py
ultralytics/models/v3/yolov3-spp.yaml
ultralytics/models/v3/yolov3-tiny.yaml
ultralytics/models/v3/yolov3.yaml
ultralytics/models/v5/yolov5-p6.yaml
ultralytics/models/v5/yolov5.yaml
ultralytics/models/v8/yolov8-cls.yaml
ultralytics/models/v8/yolov8-p2.yaml
ultralytics/models/v8/yolov8-p6.yaml
ultralytics/models/v8/yolov8-seg.yaml
ultralytics/models/v8/yolov8.yaml
ultralytics/nn/__init__.py
ultralytics/nn/autobackend.py
ultralytics/nn/autoshape.py
ultralytics/nn/modules.py
ultralytics/nn/tasks.py
ultralytics/tracker/__init__.py
ultralytics/tracker/track.py
ultralytics/tracker/cfg/botsort.yaml
ultralytics/tracker/cfg/bytetrack.yaml
ultralytics/tracker/trackers/__init__.py
ultralytics/tracker/trackers/basetrack.py
ultralytics/tracker/trackers/bot_sort.py
ultralytics/tracker/trackers/byte_tracker.py
ultralytics/tracker/utils/__init__.py
ultralytics/tracker/utils/gmc.py
ultralytics/tracker/utils/kalman_filter.py
ultralytics/tracker/utils/matching.py
ultralytics/yolo/__init__.py
ultralytics/yolo/cfg/__init__.py
ultralytics/yolo/cfg/default.yaml
ultralytics/yolo/data/__init__.py
ultralytics/yolo/data/augment.py
ultralytics/yolo/data/base.py
ultralytics/yolo/data/build.py
ultralytics/yolo/data/dataset.py
ultralytics/yolo/data/dataset_wrappers.py
yolotest-8.0.61.dist-info/LICENSE
yolotest-8.0.61.dist-info/METADATA
yolotest-8.0.61.dist-info/WHEEL
yolotest-8.0.61.dist-info/entry_points.txt
yolotest-8.0.61.dist-info/top_level.txt
yolotest-8.0.61.dist-info/RECORD
